aius/__init__.py
aius/beings/__init__.py
aius/beings/entities/__init__.py
aius/beings/events/__init__.py
aius/beings/relationships/__init__.py
aius/input_sensors/__init__.py
aius/log_memory/__init__.py
aius/log_memory/memory_handler/__init__.py
aius/log_memory/memory_manager/__init__.py
aius/log_memory/memory_pods/__init__.py
aius/log_memory/memory_storage/__init__.py
aius/log_memory/memory_types/__init__.py
aius/log_processing/__init__.py
aius/output_tools/__init__.py
aius-0.0.0.dist-info/LICENSE
aius-0.0.0.dist-info/METADATA
aius-0.0.0.dist-info/WHEEL
aius-0.0.0.dist-info/RECORD
