Metadata-Version: 2.1
Name: aius
Version: 0.0.0
Summary: AI for us: The memory system for your AI agents
License: MIT
Author: Mark Bain
Author-email: markmbain1@gmail.com
Requires-Python: >=3.8.1,<4.0
Classifier: License :: OSI Approved :: MIT License
Classifier: Programming Language :: Python :: 3
Classifier: Programming Language :: Python :: 3.9
Classifier: Programming Language :: Python :: 3.10
Classifier: Programming Language :: Python :: 3.11
Classifier: Programming Language :: Python :: 3.12
Requires-Dist: pydantic (>=2.8.2,<3.0.0)
Project-URL: Homepage, https://aius.co
Project-URL: Repository, https://github.com/markmbain/aius
